_examples/__init__.py
derobertis_project_logo/__init__.py
derobertis_project_logo/build.py
derobertis_project_logo/color.py
derobertis_project_logo/creations.py
derobertis_project_logo/gui.py
derobertis_project_logo/logo.py
derobertis_project_logo/project_logo.py
derobertis_project_logo/shape.py
derobertis_project_logo/logos/__init__.py
derobertis_project_logo/logos/main.py
derobertis_project_logo/logos/nd.py
derobertis_project_logo/logos/triangle.py
examples/__init__.py
tests/__init__.py
tests/test_logo.py
derobertis_project_logo-0.2.0.dist-info/LICENSE.md
derobertis_project_logo-0.2.0.dist-info/METADATA
derobertis_project_logo-0.2.0.dist-info/WHEEL
derobertis_project_logo-0.2.0.dist-info/entry_points.txt
derobertis_project_logo-0.2.0.dist-info/top_level.txt
derobertis_project_logo-0.2.0.dist-info/RECORD
