Metadata-Version: 2.1
Name: derobertis-project-logo
Version: 0.2.0
Summary: Nick DeRobertis' Project Logo Collection and Generator
Home-page: https://github.com/nickderobertis/derobertis-project-logo
Author: Nick DeRobertis
Author-email: whoopnip@gmail.com
License: MIT
Project-URL: Code, https://github.com/nickderobertis/derobertis-project-logo
Project-URL: Documentation, https://nickderobertis.github.io/derobertis-project-logo
Platform: UNKNOWN
Classifier: Development Status :: 3 - Alpha
Classifier: Intended Audience :: Developers
Classifier: Programming Language :: Python :: 3.6
Classifier: Programming Language :: Python :: 3.7
